src/tinycpu/defs.v
`define IDLE   3'b000
`define FETCHA 3'b001
`define FETCHB 3'b010
`define EXECA  3'b011
`define EXECB  3'b100

`define  ADD  5'b00000
`define  SUB  5'b00001
`define  MUL  5'b00010
`define  SHL  5'b00011
`define  SHR  5'b00100
`define  BAND 5'b00101
`define  BOR  5'b00110
`define  BXOR 5'b00111
`define  AND  5'b01000
`define  OR   5'b01001
`define  EQ   5'b01010
`define  NE   5'b01011
`define  GE   5'b01100
`define  LE   5'b01101
`define  GT   5'b01110
`define  LT   5'b01111
`define  NEG  5'b10000
`define  BNOT 5'b10001
`define  NOT  5'b10010

`define HALT  4'b0000
`define PUSHI 4'b0001
`define PUSH  4'b0010
`define POP   4'b0011
`define JMP   4'b0100
`define JZ    4'b0101
`define JNZ   4'b0110
`define IN    4'b1101
`define OUT   4'b1110
`define OP    4'b1111

src/tinycpu/counter.v
module counter(clk,reset,load,inc,d,q);
  parameter N = 16;
   
  input clk,reset,load,inc;
  input [N-1:0] d;
  output [N-1:0] q;
  reg [N-1:0] 	 q;

  always @(posedge clk or negedge reset)
    if(!reset) q <= 0;
    else if(load) q <= d;
    else if(inc) q <= q + 1;

endmodule

src/tinycpu/ram.v
module ram(clk, load, addr, d, q);
 parameter DWIDTH=16,AWIDTH=12,WORDS=4096;

 input clk,load;
 input [AWIDTH-1:0] addr;
 input [DWIDTH-1:0] d;
 output [DWIDTH-1:0] q;
 reg [DWIDTH-1:0] q;
 reg [DWIDTH-1:0] mem [WORDS-1:0];

 always @(posedge clk)
   begin
     if(load) mem[addr] <= d;
     q <= mem[addr];
   end

 integer i;
 initial begin
    for(i=0;i<WORDS;i=i+1)
       mem[i]=0;
 // ここにメモリの初期化（mem[12'h001]=16'h1234;など）を書く．
 end

endmodule

src/tinycpu/alu.v
`include "defs.v"

module alu(a, b, f, s);

 input [15:0] a, b;
 input [4:0] 	f;
 output [15:0] s;
 reg  [15:0] 	 s;
 wire [15:0] x, y;

 assign x = a + 16'h8000;
 assign y = b + 16'h8000;
  
 always @(a or b or x or y or f)
   case(f)
     `ADD : s = b + a;
     `SUB : s = b - a;
     `MUL : s = b * a;
     `SHL : s = b << a;
     `SHR : s = b >> a;
     `BAND: s = b & a;
     `BOR : s = b | a;
     `BXOR: s = b ^ a;
     `AND : s = b && a;
     `OR  : s = b || a;
     `EQ  : s = b == a;
     `NE  : s = b != a;
     `GE  : s = y >= x;
     `LE  : s = y <= x;
     `GT  : s = y > x;
     `LT  : s = y < x;
     `NEG : s = -a;
     `BNOT : s = ~a;
     `NOT : s = !a;
     default : s = 16'hxxxx;
   endcase

endmodule

src/tinycpu/stack.v
module stack(clk, reset, load, push, pop, d, qtop, qnext);
  parameter N = 8;
	 
  input clk, reset, load, push, pop;
  input [15:0] d;
  output [15:0] qtop, qnext;
  reg [15:0] q [0:N-1];

  assign qtop = q[0];
  assign qnext = q[1];
   
  always @(posedge clk or negedge reset)
    if(!reset) q[0] <= 0;
    else if(load) q[0] <= d;
    else if(pop) q[0] <= q[1];

  integer i;
  always @(posedge clk or negedge reset)
    for(i=1;i< N-1;i=i+1)
      if(!reset) q[i] <= 0;
      else if(push) q[i] <= q[i-1];
      else if(pop) q[i] <= q[i+1];
   
  always @(posedge clk or negedge reset)
    if(!reset) q[N-1] <= 0;
    else if(push) q[N-1] <= q[N-2];

endmodule

src/tinycpu/state.v
`include "defs.v"

module state(clk,reset,run,cont,halt,cs);
  
  input clk, reset, run, cont, halt;
  output [2:0] cs;
  reg [2:0]cs;

  always @(posedge clk or negedge reset)
    if(!reset) cs <= `IDLE;
    else
      case(cs)
        `IDLE: if(run) cs <= `FETCHA;
        `FETCHA: cs <= `FETCHB;
        `FETCHB: cs <= `EXECA;
        `EXECA: if(halt) cs <= `IDLE;
                else if(cont) cs <= `EXECB;
                else cs <= `FETCHA;
        `EXECB: cs <= `FETCHA;
        default: cs <= 3'bxxx;
      endcase

endmodule

src/tinycpu/tinycpu.v
`include "defs.v"

module tinycpu(clk, reset, run, in, cs, pcout, irout, qtop, abus, dbus, out);

  input clk,reset,run;
  input [15:0] in;
  output [2:0] cs;
  output [15:0] irout, qtop, dbus, out;
  output [11:0] pcout, abus;
  wire [15:0] qnext, ramout, aluout;
  reg [11:0] abus;
  reg halt, cont, pcinc, push, pop, abus2pc, dbus2ir, dbus2qtop, dbus2ram,
      dbus2obuf, pc2abus, ir2abus, ir2dbus, qtop2dbus, alu2dbus, ram2dbus,
      in2dbus;

  counter #(12) pc0(.clk(clk), .reset(reset), .load(abus2pc), .inc(pcinc),
                    .d(abus), .q(pcout));
  counter #(16) ir0(.clk(clk), .reset(reset), .load(dbus2ir), .inc(0),
                   .d(dbus), .q(irout));
  state state0(.clk(clk), .reset(reset), .run(run), .cont(cont),
               .halt(halt), .cs(cs));
  stack stack0(.clk(clk), .reset(reset), .load(dbus2qtop), .push(push),
               .pop(pop), .d(dbus), .qtop(qtop), .qnext(qnext));
  alu alu0(.a(qtop), .b(qnext), .f(irout[4:0]), .s(aluout));
  ram #(16,12,4096) ram0(.clk(clk), .load(dbus2ram), .addr(abus[11:0]),
                         .d(dbus), .q(ramout));
  counter #(16) obuf0(.clk(clk), .reset(reset), .load(dbus2obuf), .inc(0),
                      .d(dbus), .q(out));
  
  always @(pc2abus or ir2abus or pcout or irout)
    if(pc2abus) abus <= pcout;
    else if(ir2abus) abus <= irout[11:0];
    else abus <= 12'hxxx;

  assign dbus = ir2dbus ? {{4{irout[11]}},irout[11:0]} : 16'hzzzz;
  assign dbus = qtop2dbus ? qtop : 16'hzzzz;
  assign dbus = alu2dbus ? aluout : 16'hzzzz;
  assign dbus = ram2dbus ? ramout : 16'hzzzz;
  assign dbus = in2dbus ? in : 16'hzzzz;

  always @(cs or irout or qtop)
    begin
      halt = 0; pcinc = 0; push = 0; pop = 0; cont = 0; abus2pc = 0;
      dbus2ir = 0; dbus2qtop = 0; dbus2ram = 0; dbus2obuf = 0; pc2abus = 0;
      ir2abus = 0; ir2dbus = 0; qtop2dbus = 0; alu2dbus = 0; ram2dbus = 0;
      in2dbus = 0;
      if(cs == `FETCHA) 
        begin
          pcinc = 1; pc2abus = 1;
        end
      else if(cs == `FETCHB)
        begin
          ram2dbus = 1; dbus2ir = 1;
        end
      else if(cs == `EXECA)
        case(irout[15:12])
        `PUSHI:
           begin
             ir2dbus = 1; dbus2qtop = 1; push = 1;
           end	 
        `PUSH:
           begin
             ir2abus = 1; cont = 1;
           end
        `POP:
           begin
             ir2abus = 1; qtop2dbus = 1; dbus2ram = 1; pop = 1;
           end
        `JMP:
           begin
             ir2abus = 1; abus2pc = 1;
           end
        `JZ:
           begin
             if(qtop == 0) 
               begin
                 ir2abus = 1; abus2pc = 1;
               end
             pop = 1;
           end
        `JNZ:
           begin
             if(qtop != 0) 
               begin
                 ir2abus = 1; abus2pc = 1;
               end
             pop = 1;
           end
        `IN:
           begin
             in2dbus = 1; dbus2qtop = 1; push = 1;
           end
        `OUT:
           begin
             qtop2dbus = 1; dbus2obuf = 1; pop = 1;
           end
        `OP:
           begin
             alu2dbus = 1; dbus2qtop = 1;
             if(irout[4] == 0) pop = 1;
           end
        default:
           halt = 1;
        endcase
      else if(cs == `EXECB)
        if(irout[15:12]==`PUSH)
          begin
          ram2dbus = 1; dbus2qtop = 1; push = 1;
        end
    end

endmodule

src/tinycpu/tinycpu_test.v
module tinycpu_test;

  reg clk,reset,run;
  reg [15:0] in;
  wire [2:0] cs;
  wire [15:0] irout, qtop, dbus, out;
  wire [11:0] pcout, abus;

  tinycpu tinycpu(clk, reset, run, in, cs, pcout, irout, qtop, abus, dbus, out);

  always #5  clk = ~clk;

  initial begin
    clk = 0; reset = 0; run = 0; in = 0;
    #50 run = 1;
    #10 in = 2;
    #100 in = 5;
    #500 $finish;
  end

  initial begin
        $monitor("clk=%d, reset=%d, run=%d", clk, reset, run);
        $dumpfile("tinycpu.vcd");
        $dumpvars(0, tinycpu_test);
  end

endmodule

src/tinycpu/tinycpu.vcd
$date
	Thu Sep  9 02:16:18 2021
$end
$version
	Icarus Verilog
$end
$timescale
	1s
$end
$scope module tinycpu_test $end
$var wire 16 ! dbus [15:0] $end
$var wire 16 " qtop [15:0] $end
$var wire 12 # pcout [11:0] $end
$var wire 16 $ out [15:0] $end
$var wire 16 % irout [15:0] $end
$var wire 3 & cs [2:0] $end
$var wire 12 ' abus [11:0] $end
$var reg 1 ( clk $end
$var reg 16 ) in [15:0] $end
$var reg 1 * reset $end
$var reg 1 + run $end
$scope module tinycpu $end
$var wire 1 ( clk $end
$var wire 16 , dbus [15:0] $end
$var wire 16 - in [15:0] $end
$var wire 16 . qnext [15:0] $end
$var wire 16 / qtop [15:0] $end
$var wire 1 * reset $end
$var wire 1 + run $end
$var wire 16 0 ramout [15:0] $end
$var wire 12 1 pcout [11:0] $end
$var wire 16 2 out [15:0] $end
$var wire 16 3 irout [15:0] $end
$var wire 3 4 cs [2:0] $end
$var wire 16 5 aluout [15:0] $end
$var reg 12 6 abus [11:0] $end
$var reg 1 7 abus2pc $end
$var reg 1 8 alu2dbus $end
$var reg 1 9 cont $end
$var reg 1 : dbus2ir $end
$var reg 1 ; dbus2obuf $end
$var reg 1 < dbus2qtop $end
$var reg 1 = dbus2ram $end
$var reg 1 > halt $end
$var reg 1 ? in2dbus $end
$var reg 1 @ ir2abus $end
$var reg 1 A ir2dbus $end
$var reg 1 B pc2abus $end
$var reg 1 C pcinc $end
$var reg 1 D pop $end
$var reg 1 E push $end
$var reg 1 F qtop2dbus $end
$var reg 1 G ram2dbus $end
$scope module alu0 $end
$var wire 16 H a [15:0] $end
$var wire 16 I b [15:0] $end
$var wire 5 J f [4:0] $end
$var wire 16 K y [15:0] $end
$var wire 16 L x [15:0] $end
$var reg 16 M s [15:0] $end
$upscope $end
$scope module ir0 $end
$var wire 1 ( clk $end
$var wire 16 N d [15:0] $end
$var wire 1 O inc $end
$var wire 1 : load $end
$var wire 1 * reset $end
$var reg 16 P q [15:0] $end
$upscope $end
$scope module obuf0 $end
$var wire 1 ( clk $end
$var wire 16 Q d [15:0] $end
$var wire 1 R inc $end
$var wire 1 ; load $end
$var wire 1 * reset $end
$var reg 16 S q [15:0] $end
$upscope $end
$scope module pc0 $end
$var wire 1 ( clk $end
$var wire 12 T d [11:0] $end
$var wire 1 C inc $end
$var wire 1 7 load $end
$var wire 1 * reset $end
$var reg 12 U q [11:0] $end
$upscope $end
$scope module ram0 $end
$var wire 12 V addr [11:0] $end
$var wire 1 ( clk $end
$var wire 16 W d [15:0] $end
$var wire 1 = load $end
$var reg 16 X q [15:0] $end
$var integer 32 Y i [31:0] $end
$upscope $end
$scope module stack0 $end
$var wire 1 ( clk $end
$var wire 16 Z d [15:0] $end
$var wire 1 < load $end
$var wire 1 D pop $end
$var wire 1 E push $end
$var wire 16 [ qnext [15:0] $end
$var wire 16 \ qtop [15:0] $end
$var wire 1 * reset $end
$var integer 32 ] i [31:0] $end
$upscope $end
$scope module state0 $end
$var wire 1 ( clk $end
$var wire 1 9 cont $end
$var wire 1 > halt $end
$var wire 1 * reset $end
$var wire 1 + run $end
$var reg 3 ^ cs [2:0] $end
$upscope $end
$upscope $end
$upscope $end
$enddefinitions $end
#0
$dumpvars
b0 ^
b111 ]
b0 \
b0 [
bz Z
b1000000000000 Y
bx X
bz W
bx V
b0 U
bx T
b0 S
0R
bz Q
b0 P
0O
bz N
b0 M
b1000000000000000 L
b1000000000000000 K
b0 J
b0 I
b0 H
0G
0F
0E
0D
0C
0B
0A
0@
0?
0>
0=
0<
0;
0:
09
08
07
bx 6
b0 5
b0 4
b0 3
b0 2
b0 1
bx 0
b0 /
b0 .
b0 -
bz ,
0+
0*
b0 )
0(
bx '
b0 &
b0 %
b0 $
b0 #
b0 "
bz !
$end
#5
b111 ]
1(
#10
0(
#15
b111 ]
1(
#20
0(
#25
b111 ]
1(
#30
0(
#35
b111 ]
1(
#40
0(
#45
b111 ]
1(
#50
0(
1+
#55
b111 ]
1(
#60
0(
b10 )
b10 -
#65
b111 ]
1(
#70
0(
#75
b111 ]
1(
#80
0(
#85
b111 ]
1(
#90
0(
#95
b111 ]
1(
#100
0(
#105
b111 ]
1(
#110
0(
#115
b111 ]
1(
#120
0(
#125
b111 ]
1(
#130
0(
#135
b111 ]
1(
#140
0(
#145
b111 ]
1(
#150
0(
#155
b111 ]
1(
#160
0(
b101 )
b101 -
#165
b111 ]
1(
#170
0(
#175
b111 ]
1(
#180
0(
#185
b111 ]
1(
#190
0(
#195
b111 ]
1(
#200
0(
#205
b111 ]
1(
#210
0(
#215
b111 ]
1(
#220
0(
#225
b111 ]
1(
#230
0(
#235
b111 ]
1(
#240
0(
#245
b111 ]
1(
#250
0(
#255
b111 ]
1(
#260
0(
#265
b111 ]
1(
#270
0(
#275
b111 ]
1(
#280
0(
#285
b111 ]
1(
#290
0(
#295
b111 ]
1(
#300
0(
#305
b111 ]
1(
#310
0(
#315
b111 ]
1(
#320
0(
#325
b111 ]
1(
#330
0(
#335
b111 ]
1(
#340
0(
#345
b111 ]
1(
#350
0(
#355
b111 ]
1(
#360
0(
#365
b111 ]
1(
#370
0(
#375
b111 ]
1(
#380
0(
#385
b111 ]
1(
#390
0(
#395
b111 ]
1(
#400
0(
#405
b111 ]
1(
#410
0(
#415
b111 ]
1(
#420
0(
#425
b111 ]
1(
#430
0(
#435
b111 ]
1(
#440
0(
#445
b111 ]
1(
#450
0(
#455
b111 ]
1(
#460
0(
#465
b111 ]
1(
#470
0(
#475
b111 ]
1(
#480
0(
#485
b111 ]
1(
#490
0(
#495
b111 ]
1(
#500
0(
#505
b111 ]
1(
#510
0(
#515
b111 ]
1(
#520
0(
#525
b111 ]
1(
#530
0(
#535
b111 ]
1(
#540
0(
#545
b111 ]
1(
#550
0(
#555
b111 ]
1(
#560
0(
#565
b111 ]
1(
#570
0(
#575
b111 ]
1(
#580
0(
#585
b111 ]
1(
#590
0(
#595
b111 ]
1(
#600
0(
#605
b111 ]
1(
#610
0(
#615
b111 ]
1(
#620
0(
#625
b111 ]
1(
#630
0(
#635
b111 ]
1(
#640
0(
#645
b111 ]
1(
#650
0(
#655
b111 ]
1(
