src/examples/adder.v
module adder(a, b, q);
input [3:0] a, b;
output [0:3] q;

assign q = a+b;

endmodule

src/examples/adder_test.v
module adder_test;

reg [3:0] a, b;
wire [3:0] q;
parameter time_counter = 80;
integer i;

adder adder(a,b,q);

initial begin
       a = 0; b = 0;
       #100;
       // for (i = 0; i < time_counter; i=i+1) begin
       //        a <= a + 1;
       //        if ((i % 10) == 0)
       //               b <= b + 1;
       //       
       //        #5;
       // end
       
       #100 a = 1; b = 0;
       assert false report "test";
       #100 a = 2; b = 1;
       #100 a = 5; b = 7;
end

initial begin
       $monitor("a=%d, b=%d, q=%d", a, b, q);
       $dumpfile("adder.vcd");
       $dumpvars(0, adder_test);
end

endmodule

src/examples/adder.vcd
$date
	Mon Sep  6 04:03:32 2021
$end
$version
	Icarus Verilog
$end
$timescale
	1s
$end
$scope module adder_test $end
$var wire 4 ! q [3:0] $end
$var reg 4 " a [3:0] $end
$var reg 4 # b [3:0] $end
$var integer 32 $ i [31:0] $end
$scope module adder $end
$var wire 4 % a [3:0] $end
$var wire 4 & b [3:0] $end
$var wire 4 ' q [3:0] $end
$upscope $end
$upscope $end
$enddefinitions $end
#0
$dumpvars
b0 '
b0 &
b0 %
bx $
b0 #
b0 "
b0 !
$end
#100
b1 #
b1 &
b10 !
b10 '
b1 "
b1 %
b0 $
#105
b11 !
b11 '
b10 "
b10 %
b1 $
#110
b100 !
b100 '
b11 "
b11 %
b10 $
#115
b101 !
b101 '
b100 "
b100 %
b11 $
#120
b110 !
b110 '
b101 "
b101 %
b100 $
#125
b111 !
b111 '
b110 "
b110 %
b101 $
#130
b1000 !
b1000 '
b111 "
b111 %
b110 $
#135
b1001 !
b1001 '
b1000 "
b1000 %
b111 $
#140
b1010 !
b1010 '
b1001 "
b1001 %
b1000 $
#145
b1011 !
b1011 '
b1010 "
b1010 %
b1001 $
#150
b10 #
b10 &
b1101 !
b1101 '
b1011 "
b1011 %
b1010 $
#155
b1110 !
b1110 '
b1100 "
b1100 %
b1011 $
#160
b1111 !
b1111 '
b1101 "
b1101 %
b1100 $
#165
b0 !
b0 '
b1110 "
b1110 %
b1101 $
#170
b1 !
b1 '
b1111 "
b1111 %
b1110 $
#175
b10 !
b10 '
b0 "
b0 %
b1111 $
#180
b11 !
b11 '
b1 "
b1 %
b10000 $
#185
b100 !
b100 '
b10 "
b10 %
b10001 $
#190
b101 !
b101 '
b11 "
b11 %
b10010 $
#195
b110 !
b110 '
b100 "
b100 %
b10011 $
#200
b11 #
b11 &
b1000 !
b1000 '
b101 "
b101 %
b10100 $
#205
b1001 !
b1001 '
b110 "
b110 %
b10101 $
#210
b1010 !
b1010 '
b111 "
b111 %
b10110 $
#215
b1011 !
b1011 '
b1000 "
b1000 %
b10111 $
#220
b1100 !
b1100 '
b1001 "
b1001 %
b11000 $
#225
b1101 !
b1101 '
b1010 "
b1010 %
b11001 $
#230
b1110 !
b1110 '
b1011 "
b1011 %
b11010 $
#235
b1111 !
b1111 '
b1100 "
b1100 %
b11011 $
#240
b0 !
b0 '
b1101 "
b1101 %
b11100 $
#245
b1 !
b1 '
b1110 "
b1110 %
b11101 $
#250
b100 #
b100 &
b11 !
b11 '
b1111 "
b1111 %
b11110 $
#255
b100 !
b100 '
b0 "
b0 %
b11111 $
#260
b101 !
b101 '
b1 "
b1 %
b100000 $
#265
b110 !
b110 '
b10 "
b10 %
b100001 $
#270
b111 !
b111 '
b11 "
b11 %
b100010 $
#275
b1000 !
b1000 '
b100 "
b100 %
b100011 $
#280
b1001 !
b1001 '
b101 "
b101 %
b100100 $
#285
b1010 !
b1010 '
b110 "
b110 %
b100101 $
#290
b1011 !
b1011 '
b111 "
b111 %
b100110 $
#295
b1100 !
b1100 '
b1000 "
b1000 %
b100111 $
#300
b101 #
b101 &
b1110 !
b1110 '
b1001 "
b1001 %
b101000 $
#305
b1111 !
b1111 '
b1010 "
b1010 %
b101001 $
#310
b0 !
b0 '
b1011 "
b1011 %
b101010 $
#315
b1 !
b1 '
b1100 "
b1100 %
b101011 $
#320
b10 !
b10 '
b1101 "
b1101 %
b101100 $
#325
b11 !
b11 '
b1110 "
b1110 %
b101101 $
#330
b100 !
b100 '
b1111 "
b1111 %
b101110 $
#335
b101 !
b101 '
b0 "
b0 %
b101111 $
#340
b110 !
b110 '
b1 "
b1 %
b110000 $
#345
b111 !
b111 '
b10 "
b10 %
b110001 $
#350
b110 #
b110 &
b1001 !
b1001 '
b11 "
b11 %
b110010 $
#355
b1010 !
b1010 '
b100 "
b100 %
b110011 $
#360
b1011 !
b1011 '
b101 "
b101 %
b110100 $
#365
b1100 !
b1100 '
b110 "
b110 %
b110101 $
#370
b1101 !
b1101 '
b111 "
b111 %
b110110 $
#375
b1110 !
b1110 '
b1000 "
b1000 %
b110111 $
#380
b1111 !
b1111 '
b1001 "
b1001 %
b111000 $
#385
b0 !
b0 '
b1010 "
b1010 %
b111001 $
#390
b1 !
b1 '
b1011 "
b1011 %
b111010 $
#395
b10 !
b10 '
b1100 "
b1100 %
b111011 $
#400
b111 #
b111 &
b100 !
b100 '
b1101 "
b1101 %
b111100 $
#405
b101 !
b101 '
b1110 "
b1110 %
b111101 $
#410
b110 !
b110 '
b1111 "
b1111 %
b111110 $
#415
b111 !
b111 '
b0 "
b0 %
b111111 $
#420
b1000 !
b1000 '
b1 "
b1 %
b1000000 $
#425
b1001 !
b1001 '
b10 "
b10 %
b1000001 $
#430
b1010 !
b1010 '
b11 "
b11 %
b1000010 $
#435
b1011 !
b1011 '
b100 "
b100 %
b1000011 $
#440
b1100 !
b1100 '
b101 "
b101 %
b1000100 $
#445
b1101 !
b1101 '
b110 "
b110 %
b1000101 $
#450
b1000 #
b1000 &
b1111 !
b1111 '
b111 "
b111 %
b1000110 $
#455
b0 !
b0 '
b1000 "
b1000 %
b1000111 $
#460
b1 !
b1 '
b1001 "
b1001 %
b1001000 $
#465
b10 !
b10 '
b1010 "
b1010 %
b1001001 $
#470
b11 !
b11 '
b1011 "
b1011 %
b1001010 $
#475
b100 !
b100 '
b1100 "
b1100 %
b1001011 $
#480
b101 !
b101 '
b1101 "
b1101 %
b1001100 $
#485
b110 !
b110 '
b1110 "
b1110 %
b1001101 $
#490
b111 !
b111 '
b1111 "
b1111 %
b1001110 $
#495
b1000 !
b1000 '
b0 "
b0 %
b1001111 $
#500
b1010000 $
