src/examples/counter.v
module counter(CLK, RES, Q);

input CLK, RES;
output [3:0]Q;

wire CLK, RES;
reg [3:0]Q;

always @(posedge CLK or negedge RES) 
   if(RES ==1'b0)
       Q = 4'd0;
   else if(Q == 4'd9)
       Q = 4'd0;
   else
       Q = Q + 4'd1;

endmodule

src/examples/counter_test.v
module counter_test;

reg CLK, RES;
wire [3:0] Q;

counter counter(CLK, RES, Q);

always #5  CLK = ~CLK;

initial begin
       CLK = 0;
       RES = 0; #23      RES = 1; #150     $finish;
end

initial begin
       $monitor("CLK=%d, RES=%d, Q=%d", CLK, RES, Q);
       $dumpfile("counter.vcd");
       $dumpvars(0, counter_test);
end

endmodule

src/examples/counter.vcd
$date
	Fri May 14 13:30:36 2021
$end
$version
	Icarus Verilog
$end
$timescale
	1s
$end
$scope module counter_test $end
$var wire 4 ! Q [3:0] $end
$var reg 1 " CLK $end
$var reg 1 # RES $end
$scope module counter $end
$var wire 1 " CLK $end
$var wire 1 # RES $end
$var reg 4 $ Q [3:0] $end
$upscope $end
$upscope $end
$enddefinitions $end
#0
$dumpvars
b0 $
0#
0"
b0 !
$end
#5
1"
#10
0"
#15
1"
#20
0"
#23
1#
#25
b1 !
b1 $
1"
#30
0"
#35
b10 !
b10 $
1"
#40
0"
#45
b11 !
b11 $
1"
#50
0"
#55
b100 !
b100 $
1"
#60
0"
#65
b101 !
b101 $
1"
#70
0"
#75
b110 !
b110 $
1"
#80
0"
#85
b111 !
b111 $
1"
#90
0"
#95
b1000 !
b1000 $
1"
#100
0"
#105
b1001 !
b1001 $
1"
#110
0"
#115
b0 !
b0 $
1"
#120
0"
#125
b1 !
b1 $
1"
#130
0"
#135
b10 !
b10 $
1"
#140
0"
#145
b11 !
b11 $
1"
#150
0"
#155
b100 !
b100 $
1"
#160
0"
#165
b101 !
b101 $
1"
